[
    {
        "fields": {
            "date_joined": "2015-03-06T15:53:06.746Z",
            "email": "admin@example.com",
            "first_name": "",
            "groups": [],
            "is_active": true,
            "is_staff": true,
            "is_superuser": true,
            "last_login": "2015-03-06T15:53:06.746Z",
            "last_name": "",
            "password": "pbkdf2_sha256$15000$YC22hKtGp1vk$Fd9bW+Ex/LRtroSfK3LzEyUjgExFLopQPHOWB5lBaq4=",
            "user_permissions": []
        },
        "model": "liberator.user",
        "pk": 1
    }
]
